[
  {
    "when": "2024-04-26T14:50:53.263+02:00",
    "ref": "https://contrataciondelestado.es/sindicacion/licitacionesPerfilContratante/13607684",
    "at:comment": {
      "type": "ANULADA"
    }
  },
  {
    "when": "2024-04-26T12:51:52.014+02:00",
    "ref": "https://contrataciondelestado.es/sindicacion/licitacionesPerfilContratante/14726635",
    "at:comment": {
      "type": "ANULADA"
    }
  },
  {
    "when": "2024-04-26T12:02:52.893+02:00",
    "ref": "https://contrataciondelestado.es/sindicacion/licitacionesPerfilContratante/14555677",
    "at:comment": {
      "type": "ANULADA"
    }
  },
  {
    "when": "2024-04-26T10:54:09.291+02:00",
    "ref": "https://contrataciondelestado.es/sindicacion/licitacionesPerfilContratante/14714753",
    "at:comment": {
      "type": "ANULADA"
    }
  },
  {
    "when": "2024-04-25T15:56:27.109+02:00",
    "ref": "https://contrataciondelestado.es/sindicacion/licitacionesPerfilContratante/14509992",
    "at:comment": {
      "type": "ANULADA"
    }
  }
]