[
  {
    "when": "2024-03-27T14:33:14.979+01:00",
    "ref": "https://contrataciondelestado.es/sindicacion/licitacionesPerfilContratante/12823047",
    "at:comment": {
      "type": "ANULADA"
    }
  },
  {
    "when": "2024-03-27T13:51:42.244+01:00",
    "ref": "https://contrataciondelestado.es/sindicacion/licitacionesPerfilContratante/14501852",
    "at:comment": {
      "type": "ANULADA"
    }
  },
  {
    "when": "2024-03-27T13:50:38.138+01:00",
    "ref": "https://contrataciondelestado.es/sindicacion/licitacionesPerfilContratante/14588351",
    "at:comment": {
      "type": "ANULADA"
    }
  },
  {
    "when": "2024-03-27T13:41:58.001+01:00",
    "ref": "https://contrataciondelestado.es/sindicacion/licitacionesPerfilContratante/14581766",
    "at:comment": {
      "type": "ANULADA"
    }
  },
  {
    "when": "2024-03-27T13:26:09.913+01:00",
    "ref": "https://contrataciondelestado.es/sindicacion/licitacionesPerfilContratante/14545626",
    "at:comment": {
      "type": "ANULADA"
    }
  },
  {
    "when": "2024-03-27T13:13:15.274+01:00",
    "ref": "https://contrataciondelestado.es/sindicacion/licitacionesPerfilContratante/14568532",
    "at:comment": {
      "type": "ANULADA"
    }
  },
  {
    "when": "2024-03-27T12:51:07.218+01:00",
    "ref": "https://contrataciondelestado.es/sindicacion/licitacionesPerfilContratante/14606703",
    "at:comment": {
      "type": "ANULADA"
    }
  },
  {
    "when": "2024-03-27T12:40:45.338+01:00",
    "ref": "https://contrataciondelestado.es/sindicacion/licitacionesPerfilContratante/14623207",
    "at:comment": {
      "type": "ANULADA"
    }
  },
  {
    "when": "2024-03-27T10:53:21.005+01:00",
    "ref": "https://contrataciondelestado.es/sindicacion/licitacionesPerfilContratante/13549583",
    "at:comment": {
      "type": "ANULADA"
    }
  },
  {
    "when": "2024-03-27T10:29:35.969+01:00",
    "ref": "https://contrataciondelestado.es/sindicacion/licitacionesPerfilContratante/14623357",
    "at:comment": {
      "type": "ANULADA"
    }
  },
  {
    "when": "2024-03-27T09:03:00.906+01:00",
    "ref": "https://contrataciondelestado.es/sindicacion/licitacionesPerfilContratante/14615038",
    "at:comment": {
      "type": "ANULADA"
    }
  },
  {
    "when": "2024-03-27T08:22:16.335+01:00",
    "ref": "https://contrataciondelestado.es/sindicacion/licitacionesPerfilContratante/14465724",
    "at:comment": {
      "type": "ANULADA"
    }
  },
  {
    "when": "2024-03-27T08:17:07.574+01:00",
    "ref": "https://contrataciondelestado.es/sindicacion/licitacionesPerfilContratante/14555668",
    "at:comment": {
      "type": "ANULADA"
    }
  },
  {
    "when": "2024-03-26T18:03:01.014+01:00",
    "ref": "https://contrataciondelestado.es/sindicacion/licitacionesPerfilContratante/8120813",
    "at:comment": {
      "type": "ANULADA"
    }
  }
]